hydromill/__init__.py
hydromill/message/__init__.py
hydromill/message/message.py
hydromill/message/pubsub.py
hydromill-0.1a0.dist-info/LICENSE
hydromill-0.1a0.dist-info/METADATA
hydromill-0.1a0.dist-info/WHEEL
hydromill-0.1a0.dist-info/RECORD
