Metadata-Version: 2.1
Name: hydromill
Version: 0.1a0
Summary: Building event-driven applications the easy way in Python. This project is a direct port of https://github.com/ThreeDotsLabs/watermill.
Home-page: https://github.com/mczudowski/hydromill
License: MIT
Author: Marek Czudowski
Author-email: marek.czudowski@pm.me
Requires-Python: >=3.8,<4.0
Classifier: License :: OSI Approved :: MIT License
Classifier: Programming Language :: Python :: 3
Classifier: Programming Language :: Python :: 3.8
Classifier: Programming Language :: Python :: 3.9
Classifier: Programming Language :: Python :: 3.10
Classifier: Programming Language :: Python :: 3.11
Classifier: Programming Language :: Python :: 3.12
Requires-Dist: pydantic
Project-URL: Repository, https://github.com/mczudowski/hydromill
